onedrive_personal_sdk/__init__.py
onedrive_personal_sdk/const.py
onedrive_personal_sdk/exceptions.py
onedrive_personal_sdk/py.typed
onedrive_personal_sdk/clients/base.py
onedrive_personal_sdk/clients/client.py
onedrive_personal_sdk/clients/large_file_upload.py
onedrive_personal_sdk/models/items.py
onedrive_personal_sdk/models/upload.py
onedrive_personal_sdk/util/quick_xor_hash.py
onedrive_personal_sdk-0.1.1.dist-info/licenses/LICENSE
onedrive_personal_sdk-0.1.1.dist-info/METADATA
onedrive_personal_sdk-0.1.1.dist-info/WHEEL
onedrive_personal_sdk-0.1.1.dist-info/top_level.txt
onedrive_personal_sdk-0.1.1.dist-info/RECORD
