Metadata-Version: 2.4
Name: onedrive-personal-sdk
Version: 0.1.1
Summary: A package to interact with the Microsoft Graph API for personal OneDrives.
Author-email: Josef Zweck <josef@zweck.dev>
Maintainer-email: Josef Zweck <josef@zweck.dev>
License-Expression: MIT
Project-URL: Homepage, https://github.com/zweckj/onedrive-personal-sdk
Project-URL: Repository, https://github.com/zweckj/onedrive-personal-sdk
Project-URL: Documentation, https://github.com/zweckj/onedrive-personal-sdk
Keywords: OneDrive,Graph,api,async,client
Classifier: Development Status :: 5 - Production/Stable
Classifier: Framework :: AsyncIO
Classifier: Intended Audience :: Developers
Classifier: Natural Language :: English
Classifier: Programming Language :: Python
Classifier: Programming Language :: Python :: 3.12
Requires-Python: >=3.9
License-File: LICENSE
Requires-Dist: aiohttp>=3.8.1
Requires-Dist: mashumaro>=3.9.1
Provides-Extra: dev
Requires-Dist: covdefaults==2.3.0; extra == "dev"
Requires-Dist: coverage==7.6.7; extra == "dev"
Requires-Dist: syrupy==4.7.2; extra == "dev"
Requires-Dist: pytest==8.3.3; extra == "dev"
Requires-Dist: pytest-asyncio==0.24.0; extra == "dev"
Requires-Dist: pytest-cov==6.0.0; extra == "dev"
Requires-Dist: aioresponses==0.7.7; extra == "dev"
Dynamic: license-file
